aberoth_ephemeris/__init__.py
aberoth_ephemeris/__main__.py
aberoth_ephemeris/UpdateWebServer/__init__.py
aberoth_ephemeris/UpdateWebServer/varUpdateWS.py
aberoth_ephemeris/ephemeris/Ephemeris.py
aberoth_ephemeris/ephemeris/VariableSolver.py
aberoth_ephemeris/ephemeris/__init__.py
aberoth_ephemeris/ephemeris/variables.json
aberoth_ephemeris-1.0.2.dist-info/LICENSE.txt
aberoth_ephemeris-1.0.2.dist-info/METADATA
aberoth_ephemeris-1.0.2.dist-info/WHEEL
aberoth_ephemeris-1.0.2.dist-info/entry_points.txt
aberoth_ephemeris-1.0.2.dist-info/top_level.txt
aberoth_ephemeris-1.0.2.dist-info/RECORD
