Metadata-Version: 2.1
Name: aberoth-ephemeris
Version: 1.0.2
Summary: Provides predictions for scroll and lunar events in the MMO Aberoth
Home-page: https://github.com/jvandag/aberoth-ephemeris
Author: Jeremiah Vandagrift
Author-email: 
Keywords: aberoth,solar system,orbs,ephemeris
Requires-Python: >=3.8
License-File: LICENSE.txt
Requires-Dist: numpy==1.26.4
Requires-Dist: python-dotenv==1.0.1
Requires-Dist: Flask==3.0.3
Requires-Dist: Flask-Cors==4.0.1
Requires-Dist: waitress==3.0.0
Provides-Extra: dev
Requires-Dist: pytest; extra == "dev"
Requires-Dist: black; extra == "dev"
Requires-Dist: pre-commit; extra == "dev"
Requires-Dist: twine; extra == "dev"
Requires-Dist: wheel; extra == "dev"
Requires-Dist: setuptools; extra == "dev"
